MANIFEST.in
NEWS.txt
README.rst
setup.py
niteowl/__init__.py
niteowl.egg-info/PKG-INFO
niteowl.egg-info/SOURCES.txt
niteowl.egg-info/dependency_links.txt
niteowl.egg-info/entry_points.txt
niteowl.egg-info/not-zip-safe
niteowl.egg-info/top_level.txt