Metadata-Version: 1.0
Name: niteowl
Version: 0.1
Summary: Monitor file activity.
Home-page: UNKNOWN
Author: Francois Lagunas
Author-email: francois.lagunas@gmail.com
License: MIT
Keywords: filesystem monitoring
Platform: UNKNOWN
